qiskit_finance/VERSION.txt
qiskit_finance/__init__.py
qiskit_finance/exceptions.py
qiskit_finance/py.typed
qiskit_finance/version.py
qiskit_finance/applications/__init__.py
qiskit_finance/applications/estimation/__init__.py
qiskit_finance/applications/estimation/estimation_application.py
qiskit_finance/applications/estimation/european_call_delta.py
qiskit_finance/applications/estimation/european_call_pricing.py
qiskit_finance/applications/estimation/fixed_income_pricing.py
qiskit_finance/applications/optimization/__init__.py
qiskit_finance/applications/optimization/portfolio_diversification.py
qiskit_finance/applications/optimization/portfolio_optimization.py
qiskit_finance/circuit/__init__.py
qiskit_finance/circuit/library/__init__.py
qiskit_finance/circuit/library/payoff_functions/__init__.py
qiskit_finance/circuit/library/payoff_functions/european_call_delta_objective.py
qiskit_finance/circuit/library/payoff_functions/european_call_pricing_objective.py
qiskit_finance/circuit/library/payoff_functions/fixed_income_pricing_objective.py
qiskit_finance/circuit/library/probability_distributions/__init__.py
qiskit_finance/circuit/library/probability_distributions/gaussian_conditional_independence_model.py
qiskit_finance/circuit/library/probability_distributions/lognormal.py
qiskit_finance/circuit/library/probability_distributions/normal.py
qiskit_finance/circuit/library/probability_distributions/uniform.py
qiskit_finance/data_providers/__init__.py
qiskit_finance/data_providers/_base_data_provider.py
qiskit_finance/data_providers/data_on_demand_provider.py
qiskit_finance/data_providers/exchange_data_provider.py
qiskit_finance/data_providers/random_data_provider.py
qiskit_finance/data_providers/wikipedia_data_provider.py
qiskit_finance/data_providers/yahoo_data_provider.py
qiskit_finance-0.4.1.dist-info/LICENSE.txt
qiskit_finance-0.4.1.dist-info/METADATA
qiskit_finance-0.4.1.dist-info/WHEEL
qiskit_finance-0.4.1.dist-info/top_level.txt
qiskit_finance-0.4.1.dist-info/RECORD
