Metadata-Version: 2.1
Name: qiskit-finance
Version: 0.4.1
Summary: Qiskit Finance: A library of quantum computing finance experiments
Home-page: https://github.com/qiskit-community/qiskit-finance
Author: Qiskit Finance Development Team
Author-email: qiskit@us.ibm.com
License: Apache-2.0
Project-URL: Bug Tracker, https://github.com/qiskit-community/qiskit-finance/issues
Project-URL: Documentation, https://qiskit-community.github.io/qiskit-finance/
Project-URL: Source Code, https://github.com/qiskit-community/qiskit-finance
Keywords: qiskit sdk quantum finance
Classifier: Environment :: Console
Classifier: License :: OSI Approved :: Apache Software License
Classifier: Intended Audience :: Developers
Classifier: Intended Audience :: Science/Research
Classifier: Operating System :: Microsoft :: Windows
Classifier: Operating System :: MacOS
Classifier: Operating System :: POSIX :: Linux
Classifier: Programming Language :: Python :: 3 :: Only
Classifier: Programming Language :: Python :: 3.8
Classifier: Programming Language :: Python :: 3.9
Classifier: Programming Language :: Python :: 3.10
Classifier: Programming Language :: Python :: 3.11
Classifier: Programming Language :: Python :: 3.12
Classifier: Topic :: Scientific/Engineering
Requires-Python: >=3.8
License-File: LICENSE.txt
Requires-Dist: qiskit>=0.45
Requires-Dist: qiskit-algorithms>=0.2.0
Requires-Dist: qiskit-optimization>=0.6.0
Requires-Dist: scipy>=1.4
Requires-Dist: numpy>=1.17
Requires-Dist: psutil>=5
Requires-Dist: fastdtw
Requires-Dist: setuptools>=40.1.0
Requires-Dist: pandas
Requires-Dist: nasdaq-data-link
Requires-Dist: yfinance>=0.1.70
Requires-Dist: certifi
Requires-Dist: urllib3
